{
	 "spoiledLand" :
	 {
		 "text" : "Spoiled Land",
		 "moveCost" : 90,
		 "minimapUnblocked" : [ 74, 73, 74 ],
		 "minimapBlocked"   : [ 41, 40, 41 ],
		 "music" : "spoiledLand/d_openin.ogg",
		 "tiles" : "spoiled_land-terrain/PLTU",
		 "shortIdentifier" : "jf",
		 "river" : "spoiledLandToxicWaterRiver",
		 "battleFields" : ["spoiled_land_back1"],
		 "terrainViewPatterns" : "normal",
		 "type":["LAND"],
		 "rockTerrain" : "rock",
		 "horseSoundPenalty" : "",
		 "horseSound" : ""    //"horseSoundId" : 7
	 }
}
